rascal/__init__.py
rascal/cli.py
rascal/main.py
rascal/run_wrappers.py
rascal/coding/__init__.py
rascal/coding/coding_files.py
rascal/coding/corelex.py
rascal/coding/cu_analysis.py
rascal/coding/cu_summarization.py
rascal/coding/word_count_reliability_evaluation.py
rascal/transcripts/__init__.py
rascal/transcripts/transcript_tables.py
rascal/transcripts/transcription_reliability_evaluation.py
rascal/transcripts/transcription_reliability_selection.py
rascal/utils/__init__.py
rascal/utils/auxiliary.py
rascal/utils/cha_files.py
rascal/utils/logger.py
rascal/utils/tier.py
rascal/utils/tier_parsing.py
rascal_speech-1.0.0.dist-info/licenses/LICENSE.txt
rascal_speech-1.0.0.dist-info/METADATA
rascal_speech-1.0.0.dist-info/WHEEL
rascal_speech-1.0.0.dist-info/entry_points.txt
rascal_speech-1.0.0.dist-info/top_level.txt
rascal_speech-1.0.0.dist-info/RECORD
