Metadata-Version: 2.4
Name: rascal-speech
Version: 1.0.0
Summary: Resources for Analyzing Speech in Clinical Aphasiology Labs
Author: Nick McCloskey
License: MIT
Classifier: Programming Language :: Python :: 3
Classifier: License :: OSI Approved :: MIT License
Classifier: Operating System :: OS Independent
Requires-Python: >=3.12
License-File: LICENSE.txt
Requires-Dist: biopython>=1.84
Requires-Dist: contractions==0.1.73
Requires-Dist: nltk>=3.9.1
Requires-Dist: num2words>=0.5.14
Requires-Dist: numpy==1.26.4
Requires-Dist: pandas>=2.0.3
Requires-Dist: pyenchant==3.2.2
Requires-Dist: pylangacq==0.19.1
Requires-Dist: python-Levenshtein>=0.27.1
Requires-Dist: PyYAML>=6.0.2
Requires-Dist: tqdm>=4.67.1
Requires-Dist: openpyxl>=3.1.5
Requires-Dist: streamlit>=1.45.1
Requires-Dist: scipy>=1.16.0
Requires-Dist: xlsxwriter>=3.2.5
Provides-Extra: dev
Requires-Dist: pytest; extra == "dev"
Dynamic: license-file
